{"cameraMode":{"drawMode":0,"name":"Shaded","section":"Shading Mode"},"sceneLighting":true,"audioPlay":false,"sceneViewState":{"m_AlwaysRefresh":false,"showFog":true,"showSkybox":true,"showFlares":true,"showImageEffects":true,"showParticleSystems":true,"showVisualEffectGraphs":true,"m_FxEnabled":true},"in2DMode":false,"pivot":{"x":20.672466278076173,"y":16.58417510986328,"z":-22.60177230834961},"rotation":{"x":-0.3117896616458893,"y":0.45409515500068667,"z":-0.17341797053813935,"w":-0.8164060115814209},"size":1.507729411125183,"orthographic":false}